ttkthemes-stubs/METADATA.toml
ttkthemes-stubs/__init__.pyi
ttkthemes-stubs/_imgops.pyi
ttkthemes-stubs/_utils.pyi
ttkthemes-stubs/_widget.pyi
ttkthemes-stubs/py.typed
ttkthemes-stubs/themed_style.pyi
ttkthemes-stubs/themed_tk.pyi
types_ttkthemes-3.3.0.20260130.dist-info/licenses/LICENSE
types_ttkthemes-3.3.0.20260130.dist-info/METADATA
types_ttkthemes-3.3.0.20260130.dist-info/WHEEL
types_ttkthemes-3.3.0.20260130.dist-info/top_level.txt
types_ttkthemes-3.3.0.20260130.dist-info/RECORD
